ddouyin/__init__.py
ddouyin/ddouyin.py
ddouyin-0.0.6.dist-info/LICENSE
ddouyin-0.0.6.dist-info/METADATA
ddouyin-0.0.6.dist-info/WHEEL
ddouyin-0.0.6.dist-info/top_level.txt
ddouyin-0.0.6.dist-info/RECORD
