Metadata-Version: 2.1
Name: ddouyin
Version: 0.0.6
Summary: 一个下载抖音无水印视频的包
Home-page: https://github.com/yang2210670/py_study
Author: 冷大大猫
Author-email: yang2210670@163.com
License: UNKNOWN
Platform: UNKNOWN
Classifier: Programming Language :: Python :: 3
Classifier: License :: OSI Approved :: MIT License
Classifier: Operating System :: OS Independent
Requires-Python: >=3.6
